obs/__init__.py
obs/api/autoapp.py
obs/api/app/__init__.py
obs/api/app/configs/__init__.py
obs/api/app/controllers/__init__.py
obs/api/app/controllers/api/__init__.py
obs/api/app/controllers/api/admin.py
obs/api/app/controllers/api/storage.py
obs/api/app/helpers/__init__.py
obs/api/app/helpers/rest.py
obs/api/app/libs/__init__.py
obs/api/app/libs/meta_flask_env.py
obs/api/app/libs/utils.py
obs/cli/__init__.py
obs/cli/main.py
obs/cli/requirements.txt
obs/cli/admin/__init__.py
obs/cli/admin/commands.py
obs/cli/admin/credential.py
obs/cli/admin/qos.py
obs/cli/admin/usage.py
obs/cli/admin/user.py
obs/cli/admin/user_profile.py
obs/cli/storage/__init__.py
obs/cli/storage/bucket.py
obs/cli/storage/commands.py
obs/cli/storage/config.py
obs/cli/storage/gmt.py
obs/libs/__init__.py
obs/libs/admin.py
obs/libs/auth.py
obs/libs/bucket.py
obs/libs/config.py
obs/libs/credential.py
obs/libs/gmt.py
obs/libs/qos.py
obs/libs/user.py
obs/libs/utils.py
neo_obs-0.2.7.dist-info/LICENSE
neo_obs-0.2.7.dist-info/METADATA
neo_obs-0.2.7.dist-info/WHEEL
neo_obs-0.2.7.dist-info/entry_points.txt
neo_obs-0.2.7.dist-info/top_level.txt
neo_obs-0.2.7.dist-info/RECORD
