Metadata-Version: 2.1
Name: neo-obs
Version: 0.2.7
Summary: A OBS command line tools
Home-page: https://github.com/BiznetGIO/neo-obs
Author: BiznetGio
Author-email: support@biznetgio.com
License: MIT license
Keywords: cli
Platform: UNKNOWN
Classifier: Intended Audience :: Developers
Classifier: Topic :: Utilities
Classifier: License :: OSI Approved :: MIT License
Classifier: Natural Language :: English
Classifier: Operating System :: OS Independent
Classifier: Programming Language :: Python
Classifier: Programming Language :: Python :: 3.7
Requires-Dist: Click (==7.0)
Requires-Dist: boto3 (==1.9.227)
Requires-Dist: python-dotenv (==0.10.3)
Requires-Dist: requests (==2.22.0)
Requires-Dist: cloudianapi (==0.2.4)
Requires-Dist: tzlocal (==2.0.0)
Requires-Dist: bitmath (==1.3.3.1)
Requires-Dist: tabulate (==0.8.3)
Requires-Dist: xmltodict (==0.12.0)
Requires-Dist: requests-aws4auth (==0.9)
Requires-Dist: PyYAML (==5.1.2)
